prettier_prints/__init__.py
prettier_prints/ansi_styling.py
prettier_prints/prettier_prints.py
prettier_prints/prettier_printsv2.py
prettier_prints-3.0.0.dist-info/LICENSE
prettier_prints-3.0.0.dist-info/METADATA
prettier_prints-3.0.0.dist-info/WHEEL
prettier_prints-3.0.0.dist-info/top_level.txt
prettier_prints-3.0.0.dist-info/RECORD
