Metadata-Version: 2.1
Name: prettier_prints
Version: 3.0.0
Summary: Lightweight library for prettier terminal outputs and debugging similar to chalk for Javascript
Author: Dylan Stocking
Author-email: phantomleak@protonmail.com
License: MIT
Project-URL: Code Repo, https://github.com/PhantomLeak/prettier_prints
Project-URL: Bug Tracker, https://github.com/PhantomLeak/prettier_prints/issues
Keywords: prints,chalk,output
Classifier: License :: OSI Approved :: MIT License
Classifier: Programming Language :: Python
Classifier: Programming Language :: Python :: 3
Classifier: Topic :: Software Development
Classifier: Operating System :: Microsoft :: Windows
Classifier: Operating System :: Unix
Classifier: Operating System :: MacOS
License-File: LICENSE
